{
  "type" : "FeatureCollection",
  "features" : [ {
    "type" : "Feature",
    "geometry" : {
      "type" : "Point",
      "coordinates" : [ 51.3339086, 3.7138674 ]
    },
    "properties" : {
      "id" : "42385703",
      "name" : "01"
    }
  }, {
    "type" : "Feature",
    "geometry" : {
      "type" : "Point",
      "coordinates" : [ 51.3397616, 3.7352862 ]
    },
    "properties" : {
      "id" : "428622123",
      "name" : "03"
    }
  }, {
    "type" : "Feature",
    "geometry" : {
      "type" : "Point",
      "coordinates" : [ 51.2979819, 3.7182862 ]
    },
    "properties" : {
      "id" : "42321162",
      "name" : "04"
    }
  }, {
    "type" : "Feature",
    "geometry" : {
      "type" : "Point",
      "coordinates" : [ 51.4005235, 3.5475747 ]
    },
    "properties" : {
      "id" : "291524016",
      "name" : "07"
    }
  }, {
    "type" : "Feature",
    "geometry" : {
      "type" : "Point",
      "coordinates" : [ 51.4010486, 3.5476505 ]
    },
    "properties" : {
      "id" : "2505366722",
      "name" : "07"
    }
  }, {
    "type" : "Feature",
    "geometry" : {
      "type" : "Point",
      "coordinates" : [ 51.3107173, 3.7118006 ]
    },
    "properties" : {
      "id" : "42338858",
      "name" : "10"
    }
  }, {
    "type" : "Feature",
    "geometry" : {
      "type" : "Point",
      "coordinates" : [ 51.3891481, 3.447982 ]
    },
    "properties" : {
      "id" : "5021759863",
      "name" : "10"
    }
  }, {
    "type" : "Feature",
    "geometry" : {
      "type" : "Point",
      "coordinates" : [ 51.3746393, 3.4648979 ]
    },
    "properties" : {
      "id" : "42495689",
      "name" : "11"
    }
  }, {
    "type" : "Feature",
    "geometry" : {
      "type" : "Point",
      "coordinates" : [ 51.3423235, 3.7326802 ]
    },
    "properties" : {
      "id" : "42421673",
      "name" : "11"
    }
  }, {
    "type" : "Feature",
    "geometry" : {
      "type" : "Point",
      "coordinates" : [ 51.3713757, 3.4749948 ]
    },
    "properties" : {
      "id" : "1785919538",
      "name" : "12"
    }
  }, {
    "type" : "Feature",
    "geometry" : {
      "type" : "Point",
      "coordinates" : [ 51.2811067, 3.7604416 ]
    },
    "properties" : {
      "id" : "42295927",
      "name" : "12"
    }
  }, {
    "type" : "Feature",
    "geometry" : {
      "type" : "Point",
      "coordinates" : [ 51.3676602, 3.4806849 ]
    },
    "properties" : {
      "id" : "42479992",
      "name" : "13"
    }
  }, {
    "type" : "Feature",
    "geometry" : {
      "type" : "Point",
      "coordinates" : [ 51.3976548, 3.4848505 ]
    },
    "properties" : {
      "id" : "1787064253",
      "name" : "14"
    }
  }, {
    "type" : "Feature",
    "geometry" : {
      "type" : "Point",
      "coordinates" : [ 51.3474599, 3.7297517 ]
    },
    "properties" : {
      "id" : "647225932",
      "name" : "14"
    }
  }, {
    "type" : "Feature",
    "geometry" : {
      "type" : "Point",
      "coordinates" : [ 51.3882338, 3.4895984 ]
    },
    "properties" : {
      "id" : "4567051341",
      "name" : "15"
    }
  }, {
    "type" : "Feature",
    "geometry" : {
      "type" : "Point",
      "coordinates" : [ 51.2939983, 3.7540297 ]
    },
    "properties" : {
      "id" : "42315261",
      "name" : "15"
    }
  }, {
    "type" : "Feature",
    "geometry" : {
      "type" : "Point",
      "coordinates" : [ 51.3911221, 3.5180803 ]
    },
    "properties" : {
      "id" : "42525187",
      "name" : "16"
    }
  }, {
    "type" : "Feature",
    "geometry" : {
      "type" : "Point",
      "coordinates" : [ 51.3317165, 3.7732313 ]
    },
    "properties" : {
      "id" : "42380817",
      "name" : "17"
    }
  }, {
    "type" : "Feature",
    "geometry" : {
      "type" : "Point",
      "coordinates" : [ 51.3725807, 3.5092463 ]
    },
    "properties" : {
      "id" : "3521810016",
      "name" : "17"
    }
  }, {
    "type" : "Feature",
    "geometry" : {
      "type" : "Point",
      "coordinates" : [ 51.3292642, 3.6882384 ]
    },
    "properties" : {
      "id" : "4839615547",
      "name" : "18"
    }
  }, {
    "type" : "Feature",
    "geometry" : {
      "type" : "Point",
      "coordinates" : [ 51.3086886, 3.6750859 ]
    },
    "properties" : {
      "id" : "42335976",
      "name" : "19"
    }
  }, {
    "type" : "Feature",
    "geometry" : {
      "type" : "Point",
      "coordinates" : [ 51.4046007, 3.5397488 ]
    },
    "properties" : {
      "id" : "2612785781",
      "name" : "20"
    }
  }, {
    "type" : "Feature",
    "geometry" : {
      "type" : "Point",
      "coordinates" : [ 51.3197204, 3.723996 ]
    },
    "properties" : {
      "id" : "3511903809",
      "name" : "21"
    }
  }, {
    "type" : "Feature",
    "geometry" : {
      "type" : "Point",
      "coordinates" : [ 51.3681423, 3.5732731 ]
    },
    "properties" : {
      "id" : "4537977438",
      "name" : "21"
    }
  }, {
    "type" : "Feature",
    "geometry" : {
      "type" : "Point",
      "coordinates" : [ 51.3847, 3.57508 ]
    },
    "properties" : {
      "id" : "42514778",
      "name" : "22"
    }
  }, {
    "type" : "Feature",
    "geometry" : {
      "type" : "Point",
      "coordinates" : [ 51.38494, 3.5986086 ]
    },
    "properties" : {
      "id" : "42515066",
      "name" : "23"
    }
  }, {
    "type" : "Feature",
    "geometry" : {
      "type" : "Point",
      "coordinates" : [ 51.3022846, 3.3286292 ]
    },
    "properties" : {
      "id" : "3359873615",
      "name" : "23"
    }
  }, {
    "type" : "Feature",
    "geometry" : {
      "type" : "Point",
      "coordinates" : [ 51.3739717, 3.6399638 ]
    },
    "properties" : {
      "id" : "1751114556",
      "name" : "24"
    }
  }, {
    "type" : "Feature",
    "geometry" : {
      "type" : "Point",
      "coordinates" : [ 51.396355, 3.5610462 ]
    },
    "properties" : {
      "id" : "42534612",
      "name" : "25"
    }
  }, {
    "type" : "Feature",
    "geometry" : {
      "type" : "Point",
      "coordinates" : [ 51.387262, 3.5844402 ]
    },
    "properties" : {
      "id" : "42518589",
      "name" : "26"
    }
  }, {
    "type" : "Feature",
    "geometry" : {
      "type" : "Point",
      "coordinates" : [ 51.3749933, 3.5630597 ]
    },
    "properties" : {
      "id" : "42496586",
      "name" : "27"
    }
  }, {
    "type" : "Feature",
    "geometry" : {
      "type" : "Point",
      "coordinates" : [ 51.3731976, 3.6617457 ]
    },
    "properties" : {
      "id" : "42492182",
      "name" : "28"
    }
  }, {
    "type" : "Feature",
    "geometry" : {
      "type" : "Point",
      "coordinates" : [ 51.3619675, 3.3776215 ]
    },
    "properties" : {
      "id" : "1786027351",
      "name" : "29"
    }
  }, {
    "type" : "Feature",
    "geometry" : {
      "type" : "Point",
      "coordinates" : [ 51.3480025, 3.3848973 ]
    },
    "properties" : {
      "id" : "42433084",
      "name" : "30"
    }
  }, {
    "type" : "Feature",
    "geometry" : {
      "type" : "Point",
      "coordinates" : [ 51.3073461, 3.6159728 ]
    },
    "properties" : {
      "id" : "42333988",
      "name" : "31"
    }
  }, {
    "type" : "Feature",
    "geometry" : {
      "type" : "Point",
      "coordinates" : [ 51.3403688, 3.3882136 ]
    },
    "properties" : {
      "id" : "42418110",
      "name" : "31"
    }
  }, {
    "type" : "Feature",
    "geometry" : {
      "type" : "Point",
      "coordinates" : [ 51.3033834, 3.610318 ]
    },
    "properties" : {
      "id" : "42328506",
      "name" : "32"
    }
  }, {
    "type" : "Feature",
    "geometry" : {
      "type" : "Point",
      "coordinates" : [ 51.3773215, 3.3828177 ]
    },
    "properties" : {
      "id" : "1786027620",
      "name" : "32"
    }
  }, {
    "type" : "Feature",
    "geometry" : {
      "type" : "Point",
      "coordinates" : [ 51.337038, 3.6628231 ]
    },
    "properties" : {
      "id" : "247741938",
      "name" : "33"
    }
  }, {
    "type" : "Feature",
    "geometry" : {
      "type" : "Point",
      "coordinates" : [ 51.3691017, 3.4072837 ]
    },
    "properties" : {
      "id" : "42483467",
      "name" : "33"
    }
  }, {
    "type" : "Feature",
    "geometry" : {
      "type" : "Point",
      "coordinates" : [ 51.3656161, 3.4129685 ]
    },
    "properties" : {
      "id" : "42475332",
      "name" : "34"
    }
  }, {
    "type" : "Feature",
    "geometry" : {
      "type" : "Point",
      "coordinates" : [ 51.3633873, 3.6931553 ]
    },
    "properties" : {
      "id" : "42470296",
      "name" : "34"
    }
  }, {
    "type" : "Feature",
    "geometry" : {
      "type" : "Point",
      "coordinates" : [ 51.3360926, 3.6865192 ]
    },
    "properties" : {
      "id" : "42391038",
      "name" : "35"
    }
  }, {
    "type" : "Feature",
    "geometry" : {
      "type" : "Point",
      "coordinates" : [ 51.338593, 3.4170839 ]
    },
    "properties" : {
      "id" : "2484044154",
      "name" : "35"
    }
  }, {
    "type" : "Feature",
    "geometry" : {
      "type" : "Point",
      "coordinates" : [ 51.3070321, 3.682974 ]
    },
    "properties" : {
      "id" : "3512184579",
      "name" : "36"
    }
  }, {
    "type" : "Feature",
    "geometry" : {
      "type" : "Point",
      "coordinates" : [ 51.3372799, 3.4320161 ]
    },
    "properties" : {
      "id" : "42411132",
      "name" : "36"
    }
  }, {
    "type" : "Feature",
    "geometry" : {
      "type" : "Point",
      "coordinates" : [ 51.3705284, 3.6877687 ]
    },
    "properties" : {
      "id" : "647222495",
      "name" : "37"
    }
  }, {
    "type" : "Feature",
    "geometry" : {
      "type" : "Point",
      "coordinates" : [ 51.3688345, 3.6886812 ]
    },
    "properties" : {
      "id" : "647222499",
      "name" : "37"
    }
  }, {
    "type" : "Feature",
    "geometry" : {
      "type" : "Point",
      "coordinates" : [ 51.3854437, 3.4337869 ]
    },
    "properties" : {
      "id" : "291532797",
      "name" : "37"
    }
  }, {
    "type" : "Feature",
    "geometry" : {
      "type" : "Point",
      "coordinates" : [ 51.3669262, 3.4407114 ]
    },
    "properties" : {
      "id" : "42477738",
      "name" : "38"
    }
  }, {
    "type" : "Feature",
    "geometry" : {
      "type" : "Point",
      "coordinates" : [ 51.3617354, 3.4295846 ]
    },
    "properties" : {
      "id" : "42465938",
      "name" : "39"
    }
  }, {
    "type" : "Feature",
    "geometry" : {
      "type" : "Point",
      "coordinates" : [ 51.3234197, 3.6155376 ]
    },
    "properties" : {
      "id" : "42362885",
      "name" : "39"
    }
  }, {
    "type" : "Feature",
    "geometry" : {
      "type" : "Point",
      "coordinates" : [ 51.3315015, 3.4759651 ]
    },
    "properties" : {
      "id" : "42380569",
      "name" : "40"
    }
  }, {
    "type" : "Feature",
    "geometry" : {
      "type" : "Point",
      "coordinates" : [ 51.3507436, 3.4599413 ]
    },
    "properties" : {
      "id" : "42438848",
      "name" : "41"
    }
  }, {
    "type" : "Feature",
    "geometry" : {
      "type" : "Point",
      "coordinates" : [ 51.2804292, 3.5469519 ]
    },
    "properties" : {
      "id" : "388333724",
      "name" : "41"
    }
  }, {
    "type" : "Feature",
    "geometry" : {
      "type" : "Point",
      "coordinates" : [ 51.3499475, 3.5063164 ]
    },
    "properties" : {
      "id" : "42437310",
      "name" : "42"
    }
  }, {
    "type" : "Feature",
    "geometry" : {
      "type" : "Point",
      "coordinates" : [ 51.3503118, 3.5080054 ]
    },
    "properties" : {
      "id" : "3521809754",
      "name" : "42"
    }
  }, {
    "type" : "Feature",
    "geometry" : {
      "type" : "Point",
      "coordinates" : [ 51.3530116, 3.5294493 ]
    },
    "properties" : {
      "id" : "42443974",
      "name" : "43"
    }
  }, {
    "type" : "Feature",
    "geometry" : {
      "type" : "Point",
      "coordinates" : [ 51.3413517, 3.4507218 ]
    },
    "properties" : {
      "id" : "1456343169",
      "name" : "44"
    }
  }, {
    "type" : "Feature",
    "geometry" : {
      "type" : "Point",
      "coordinates" : [ 51.2976029, 3.6129035 ]
    },
    "properties" : {
      "id" : "388332594",
      "name" : "45"
    }
  }, {
    "type" : "Feature",
    "geometry" : {
      "type" : "Point",
      "coordinates" : [ 51.3269042, 3.486979 ]
    },
    "properties" : {
      "id" : "42370391",
      "name" : "46"
    }
  }, {
    "type" : "Feature",
    "geometry" : {
      "type" : "Point",
      "coordinates" : [ 51.3231494, 3.4868868 ]
    },
    "properties" : {
      "id" : "42362206",
      "name" : "47"
    }
  }, {
    "type" : "Feature",
    "geometry" : {
      "type" : "Point",
      "coordinates" : [ 51.2759297, 3.6937529 ]
    },
    "properties" : {
      "id" : "297609823",
      "name" : "48"
    }
  }, {
    "type" : "Feature",
    "geometry" : {
      "type" : "Point",
      "coordinates" : [ 51.293661, 3.4961442 ]
    },
    "properties" : {
      "id" : "42314451",
      "name" : "49"
    }
  }, {
    "type" : "Feature",
    "geometry" : {
      "type" : "Point",
      "coordinates" : [ 51.3398343, 3.6023177 ]
    },
    "properties" : {
      "id" : "42416653",
      "name" : "50"
    }
  }, {
    "type" : "Feature",
    "geometry" : {
      "type" : "Point",
      "coordinates" : [ 51.3359793, 3.366478 ]
    },
    "properties" : {
      "id" : "247742348",
      "name" : "50"
    }
  }, {
    "type" : "Feature",
    "geometry" : {
      "type" : "Point",
      "coordinates" : [ 51.3083718, 3.5587177 ]
    },
    "properties" : {
      "id" : "42335569",
      "name" : "52"
    }
  }, {
    "type" : "Feature",
    "geometry" : {
      "type" : "Point",
      "coordinates" : [ 51.3228457, 3.369163 ]
    },
    "properties" : {
      "id" : "42361459",
      "name" : "53"
    }
  }, {
    "type" : "Feature",
    "geometry" : {
      "type" : "Point",
      "coordinates" : [ 51.3281247, 3.5504087 ]
    },
    "properties" : {
      "id" : "42373298",
      "name" : "53"
    }
  }, {
    "type" : "Feature",
    "geometry" : {
      "type" : "Point",
      "coordinates" : [ 51.3020358, 3.3582689 ]
    },
    "properties" : {
      "id" : "300464008",
      "name" : "54"
    }
  }, {
    "type" : "Feature",
    "geometry" : {
      "type" : "Point",
      "coordinates" : [ 51.2563042, 3.4150653 ]
    },
    "properties" : {
      "id" : "384919036",
      "name" : "56"
    }
  }, {
    "type" : "Feature",
    "geometry" : {
      "type" : "Point",
      "coordinates" : [ 51.2586745, 3.419305 ]
    },
    "properties" : {
      "id" : "42262593",
      "name" : "61"
    }
  }, {
    "type" : "Feature",
    "geometry" : {
      "type" : "Point",
      "coordinates" : [ 51.25274, 3.474 ]
    },
    "properties" : {
      "id" : "42255729",
      "name" : "62"
    }
  }, {
    "type" : "Feature",
    "geometry" : {
      "type" : "Point",
      "coordinates" : [ 51.2738749, 3.4290472 ]
    },
    "properties" : {
      "id" : "42285317",
      "name" : "70"
    }
  }, {
    "type" : "Feature",
    "geometry" : {
      "type" : "Point",
      "coordinates" : [ 51.2709573, 3.465337 ]
    },
    "properties" : {
      "id" : "879415030",
      "name" : "71"
    }
  }, {
    "type" : "Feature",
    "geometry" : {
      "type" : "Point",
      "coordinates" : [ 51.26969, 3.47225 ]
    },
    "properties" : {
      "id" : "42279345",
      "name" : "72"
    }
  }, {
    "type" : "Feature",
    "geometry" : {
      "type" : "Point",
      "coordinates" : [ 51.2954461, 3.4628007 ]
    },
    "properties" : {
      "id" : "42317476",
      "name" : "73"
    }
  }, {
    "type" : "Feature",
    "geometry" : {
      "type" : "Point",
      "coordinates" : [ 51.2726542, 3.494832 ]
    },
    "properties" : {
      "id" : "2716046271",
      "name" : "74"
    }
  }, {
    "type" : "Feature",
    "geometry" : {
      "type" : "Point",
      "coordinates" : [ 51.3060251, 3.4571092 ]
    },
    "properties" : {
      "id" : "42331800",
      "name" : "76"
    }
  }, {
    "type" : "Feature",
    "geometry" : {
      "type" : "Point",
      "coordinates" : [ 51.3087564, 3.4933776 ]
    },
    "properties" : {
      "id" : "42336200",
      "name" : "77"
    }
  }, {
    "type" : "Feature",
    "geometry" : {
      "type" : "Point",
      "coordinates" : [ 51.3203878, 3.4877606 ]
    },
    "properties" : {
      "id" : "42357293",
      "name" : "78"
    }
  }, {
    "type" : "Feature",
    "geometry" : {
      "type" : "Point",
      "coordinates" : [ 51.3823133, 3.4619472 ]
    },
    "properties" : {
      "id" : "42510697",
      "name" : "81"
    }
  }, {
    "type" : "Feature",
    "geometry" : {
      "type" : "Point",
      "coordinates" : [ 51.3901304, 3.4655218 ]
    },
    "properties" : {
      "id" : "42523823",
      "name" : "82"
    }
  }, {
    "type" : "Feature",
    "geometry" : {
      "type" : "Point",
      "coordinates" : [ 51.3945324, 3.46887 ]
    },
    "properties" : {
      "id" : "685094300",
      "name" : "83"
    }
  }, {
    "type" : "Feature",
    "geometry" : {
      "type" : "Point",
      "coordinates" : [ 51.3577598, 3.4833184 ]
    },
    "properties" : {
      "id" : "42456160",
      "name" : "84"
    }
  }, {
    "type" : "Feature",
    "geometry" : {
      "type" : "Point",
      "coordinates" : [ 51.3958563, 3.494226 ]
    },
    "properties" : {
      "id" : "2601017007",
      "name" : "85"
    }
  }, {
    "type" : "Feature",
    "geometry" : {
      "type" : "Point",
      "coordinates" : [ 51.4436134, 3.5958351 ]
    },
    "properties" : {
      "id" : "42640020",
      "name" : "86"
    }
  }, {
    "type" : "Feature",
    "geometry" : {
      "type" : "Point",
      "coordinates" : [ 51.2614093, 3.5296731 ]
    },
    "properties" : {
      "id" : "247742119",
      "name" : "86"
    }
  }, {
    "type" : "Feature",
    "geometry" : {
      "type" : "Point",
      "coordinates" : [ 51.3571597, 3.3543374 ]
    },
    "properties" : {
      "id" : "5498511004",
      "name" : "86"
    }
  }, {
    "type" : "Feature",
    "geometry" : {
      "type" : "Point",
      "coordinates" : [ 51.244121, 3.5160632 ]
    },
    "properties" : {
      "id" : "369332592",
      "name" : "92"
    }
  }, {
    "type" : "Feature",
    "geometry" : {
      "type" : "Point",
      "coordinates" : [ 51.3137048, 3.3650056 ]
    },
    "properties" : {
      "id" : "42344224",
      "name" : "93"
    }
  }, {
    "type" : "Feature",
    "geometry" : {
      "type" : "Point",
      "coordinates" : [ 51.3059022, 3.379685 ]
    },
    "properties" : {
      "id" : "711026634",
      "name" : "94"
    }
  }, {
    "type" : "Feature",
    "geometry" : {
      "type" : "Point",
      "coordinates" : [ 51.3255016, 3.4352093 ]
    },
    "properties" : {
      "id" : "42367146",
      "name" : "95"
    }
  }, {
    "type" : "Feature",
    "geometry" : {
      "type" : "Point",
      "coordinates" : [ 51.3124495, 3.3877957 ]
    },
    "properties" : {
      "id" : "42341611",
      "name" : "96"
    }
  }, {
    "type" : "Feature",
    "geometry" : {
      "type" : "Point",
      "coordinates" : [ 51.3118037, 3.3966074 ]
    },
    "properties" : {
      "id" : "42340627",
      "name" : "97"
    }
  }, {
    "type" : "Feature",
    "geometry" : {
      "type" : "Point",
      "coordinates" : [ 51.3095451, 3.3824712 ]
    },
    "properties" : {
      "id" : "42337141",
      "name" : "98"
    }
  }, {
    "type" : "Feature",
    "geometry" : {
      "type" : "Point",
      "coordinates" : [ 51.3044054, 3.390239 ]
    },
    "properties" : {
      "id" : "1456343161",
      "name" : "99"
    }
  } ]
}